paper_find_mcp/__init__.py
paper_find_mcp/paper.py
paper_find_mcp/server.py
paper_find_mcp/academic_platforms/__init__.py
paper_find_mcp/academic_platforms/arxiv.py
paper_find_mcp/academic_platforms/biorxiv.py
paper_find_mcp/academic_platforms/crossref.py
paper_find_mcp/academic_platforms/google_scholar.py
paper_find_mcp/academic_platforms/hub.py
paper_find_mcp/academic_platforms/iacr.py
paper_find_mcp/academic_platforms/medrxiv.py
paper_find_mcp/academic_platforms/pubmed.py
paper_find_mcp/academic_platforms/repec.py
paper_find_mcp/academic_platforms/sci_hub.py
paper_find_mcp/academic_platforms/semantic.py
paper_find_mcp-0.2.1.dist-info/METADATA
paper_find_mcp-0.2.1.dist-info/WHEEL
paper_find_mcp-0.2.1.dist-info/entry_points.txt
paper_find_mcp-0.2.1.dist-info/licenses/LICENSE
paper_find_mcp-0.2.1.dist-info/RECORD
