Metadata-Version: 2.4
Name: paper-find-mcp
Version: 0.2.1
Summary: A MCP server for searching and downloading academic papers from multiple sources.
Author-email: Haibo Lu <luhaibo1985@gmail.com>
License-File: LICENSE
Requires-Python: >=3.10
Requires-Dist: beautifulsoup4>=4.12.0
Requires-Dist: fastmcp
Requires-Dist: feedparser
Requires-Dist: httpx[socks]>=0.28.1
Requires-Dist: lxml>=4.9.0
Requires-Dist: mcp[cli]>=1.6.0
Requires-Dist: pydantic>=2.0
Requires-Dist: pymupdf4llm>=0.2.0
Requires-Dist: requests
